metalstack/__init__.py
metalstack/admin/__init__.py
metalstack/admin/v2/__init__.py
metalstack/admin/v2/filesystem_connect.py
metalstack/admin/v2/filesystem_pb2.py
metalstack/admin/v2/filesystem_pb2.pyi
metalstack/admin/v2/image_connect.py
metalstack/admin/v2/image_pb2.py
metalstack/admin/v2/image_pb2.pyi
metalstack/admin/v2/ip_connect.py
metalstack/admin/v2/ip_pb2.py
metalstack/admin/v2/ip_pb2.pyi
metalstack/admin/v2/machine_connect.py
metalstack/admin/v2/machine_pb2.py
metalstack/admin/v2/machine_pb2.pyi
metalstack/admin/v2/network_connect.py
metalstack/admin/v2/network_pb2.py
metalstack/admin/v2/network_pb2.pyi
metalstack/admin/v2/partition_connect.py
metalstack/admin/v2/partition_pb2.py
metalstack/admin/v2/partition_pb2.pyi
metalstack/admin/v2/project_connect.py
metalstack/admin/v2/project_pb2.py
metalstack/admin/v2/project_pb2.pyi
metalstack/admin/v2/size_connect.py
metalstack/admin/v2/size_pb2.py
metalstack/admin/v2/size_pb2.pyi
metalstack/admin/v2/switch_connect.py
metalstack/admin/v2/switch_pb2.py
metalstack/admin/v2/switch_pb2.pyi
metalstack/admin/v2/task_connect.py
metalstack/admin/v2/task_pb2.py
metalstack/admin/v2/task_pb2.pyi
metalstack/admin/v2/tenant_connect.py
metalstack/admin/v2/tenant_pb2.py
metalstack/admin/v2/tenant_pb2.pyi
metalstack/admin/v2/token_connect.py
metalstack/admin/v2/token_pb2.py
metalstack/admin/v2/token_pb2.pyi
metalstack/admin/v2/vpn_connect.py
metalstack/admin/v2/vpn_pb2.py
metalstack/admin/v2/vpn_pb2.pyi
metalstack/api/__init__.py
metalstack/api/v2/__init__.py
metalstack/api/v2/common_pb2.py
metalstack/api/v2/common_pb2.pyi
metalstack/api/v2/filesystem_connect.py
metalstack/api/v2/filesystem_pb2.py
metalstack/api/v2/filesystem_pb2.pyi
metalstack/api/v2/health_connect.py
metalstack/api/v2/health_pb2.py
metalstack/api/v2/health_pb2.pyi
metalstack/api/v2/image_connect.py
metalstack/api/v2/image_pb2.py
metalstack/api/v2/image_pb2.pyi
metalstack/api/v2/ip_connect.py
metalstack/api/v2/ip_pb2.py
metalstack/api/v2/ip_pb2.pyi
metal_stack_api-0.0.41.dist-info/METADATA
metal_stack_api-0.0.41.dist-info/WHEEL
metal_stack_api-0.0.41.dist-info/top_level.txt
metal_stack_api-0.0.41.dist-info/RECORD
