Metadata-Version: 2.4
Name: metal-stack-api
Version: 0.0.41
Summary: Python API client for metal-stack api
Home-page: https://github.com/metal-stack/api
Author: metal-stack authors
License: MIT
Keywords: metal-stack,metal-apiserver
Classifier: Intended Audience :: Developers
Classifier: Natural Language :: English
Classifier: Operating System :: POSIX
Classifier: Programming Language :: Python :: 3
Classifier: Programming Language :: Python :: 3.11
Classifier: Programming Language :: Python :: 3.12
Classifier: Programming Language :: Python :: 3.13
Requires-Dist: connect-python>=0.7.0
Requires-Dist: protovalidate>=1.1.0
Dynamic: author
Dynamic: classifier
Dynamic: description
Dynamic: home-page
Dynamic: keywords
Dynamic: license
Dynamic: requires-dist
Dynamic: summary
